CHANGES.txt
README.txt
setup.py
collective/__init__.py
collective.contentgovernance.egg-info/PKG-INFO
collective.contentgovernance.egg-info/SOURCES.txt
collective.contentgovernance.egg-info/dependency_links.txt
collective.contentgovernance.egg-info/entry_points.txt
collective.contentgovernance.egg-info/namespace_packages.txt
collective.contentgovernance.egg-info/not-zip-safe
collective.contentgovernance.egg-info/requires.txt
collective.contentgovernance.egg-info/top_level.txt
collective/contentgovernance/__init__.py
collective/contentgovernance/configure.zcml
collective/contentgovernance/indexer.py
collective/contentgovernance/manage_i18n.sh
collective/contentgovernance/schemaextender.py
collective/contentgovernance/testing.py
collective/contentgovernance/browser/__init__.py
collective/contentgovernance/browser/catalogghosts.py
collective/contentgovernance/browser/configure.zcml
collective/contentgovernance/browser/responsibilities.pt
collective/contentgovernance/browser/responsibilities.py
collective/contentgovernance/locales/collective.contentgovernance.pot
collective/contentgovernance/locales/en/LC_MESSAGES/collective.contentgovernance.po
collective/contentgovernance/locales/no/LC_MESSAGES/collective.contentgovernance.mo
collective/contentgovernance/locales/no/LC_MESSAGES/collective.contentgovernance.po
collective/contentgovernance/profiles/default/actions.xml
collective/contentgovernance/profiles/default/catalog.xml
collective/contentgovernance/profiles/default/metadata.xml
collective/contentgovernance/profiles/default/portal_atct.xml
collective/contentgovernance/profiles/default/rolemap.xml
collective/contentgovernance/tests/__init__.py
collective/contentgovernance/tests/test_integration_unit.py
docs/LICENSE.GPL
docs/LICENSE.txt