Metadata-Version: 1.0
Name: collective.contentgovernance
Version: 1.1
Summary: UNKNOWN
Home-page: http://pypi.python.org/pypi/collective.contentgovernance
Author: Jarn AS
Author-email: info@jarn.com
License: GPL
Platform: UNKNOWN
Classifier: Framework :: Plone
Classifier: Programming Language :: Python
